LICENSE
bayes_ab/__init__.py
bayes_ab/experiments/__init__.py
bayes_ab/experiments/base.py
bayes_ab/experiments/binary.py
bayes_ab/experiments/delta_lognormal.py
bayes_ab/experiments/discrete.py
bayes_ab/experiments/normal.py
bayes_ab/experiments/poisson.py
bayes_ab/metrics/__init__.py
bayes_ab/metrics/evaluation.py
bayes_ab/metrics/posteriors.py
bayes_ab/utilities/__init__.py
bayes_ab/utilities/common.py
bayes_ab/utilities/logging.conf
bayes_ab/utilities/logging.py
bayes_ab/utilities/output.py
bayes_ab-0.4.3.dist-info/METADATA
bayes_ab-0.4.3.dist-info/LICENSE
bayes_ab-0.4.3.dist-info/WHEEL
bayes_ab-0.4.3.dist-info/RECORD
