Metadata-Version: 2.1
Name: bayes-ab
Version: 0.4.3
Summary: Bayesian A/B testing.
Home-page: https://github.com/PlatosTwin/bayes_ab
License: MIT
Keywords: ab testing,bayes,bayesian statistics
Author: Nikita Bogdanov
Requires-Python: >=3.8,<4.0
Classifier: License :: OSI Approved :: MIT License
Classifier: Programming Language :: Python :: 3
Classifier: Programming Language :: Python :: 3.8
Classifier: Programming Language :: Python :: 3.9
Classifier: Programming Language :: Python :: 3.10
Classifier: Programming Language :: Python :: 3.11
Requires-Dist: matplotlib (>=3.6.2,<4.0.0)
Requires-Dist: numpy (>=1.22.0,<2.0.0)
Requires-Dist: prettytable (>=3.5.0,<4.0.0)
Requires-Dist: scipy (>=1.9.3,<2.0.0)
Project-URL: Repository, https://github.com/PlatosTwin/bayes_ab
